{
  "type": "minecraft:chest",
  "pools": [
    {
      "rolls": {
        "min": 6,
        "max": 10
      },
      "entries": [
        {
          "type": "minecraft:item",
          "weight": 4,
          "name": "minecraft:kelp"
        },
        {
          "type": "minecraft:item",
          "weight": 4,
          "name": "minecraft:seagrass"
        },
        {
          "type": "minecraft:item",
          "weight": 5,
          "name": "minecraft:cod"
        },
        {
          "type": "minecraft:item",
          "weight": 5,
          "name": "minecraft:salmon"
        },
        {
          "type": "minecraft:item",
          "weight": 1,
          "name": "minecraft:cod_bucket"
        },
        {
          "type": "minecraft:item",
          "weight": 1,
          "name": "minecraft:salmon_bucket"
        },
        {
          "type": "minecraft:item",
          "weight": 4,
          "name": "minecraft:iron_ingot"
        },
        {
          "type": "minecraft:item",
          "weight": 5,
          "name": "minecraft:iron_nugget"
        },
        {
          "type": "minecraft:item",
          "weight": 2,
          "name": "minecraft:pufferfish"
        },
        {
          "type": "minecraft:item",
          "weight": 3,
          "name": "minecraft:prismarine_crystals"
        },
        {
          "type": "minecraft:item",
          "weight": 3,
          "name": "minecraft:prismarine_shard"
        },
        {
          "type": "minecraft:item",
          "weight": 3,
          "name": "minecraft:string"
        },
        {
          "type": "minecraft:item",
          "weight": 3,
          "name": "minecraft:sea_pickle"
        },
        {
          "type": "minecraft:item",
          "weight": 4,
          "name": "minecraft:lapis_lazuli"
        },
        {
          "type": "minecraft:item",
          "weight": 4,
          "name": "minecraft:copper_ingot"
        },
        {
          "type": "minecraft:item",
          "weight": 2,
          "name": "greekfantasy:mirror"
        }
      ]
    },
    {
      "rolls": {
        "min": 0,
        "max": 2
      },
      "entries": [
        {
          "type": "minecraft:item",
          "weight": 2,
          "name": "minecraft:sponge"
        },
        {
          "type": "minecraft:item",
          "weight": 4,
          "name": "minecraft:turtle_egg"
        },
        {
          "type": "minecraft:item",
          "weight": 5,
          "name": "minecraft:nautilus_shell"
        },
        {
          "type": "minecraft:item",
          "weight": 1,
          "name": "minecraft:trident",
          "functions": [
            {
              "function": "minecraft:enchant_with_levels",
              "levels": 20
            },
            {
              "function": "minecraft:set_damage",
              "damage": {
                "min": 0,
                "max": 225
              }
            }
          ]
        },
        {
          "type": "minecraft:item",
          "weight": 3,
          "name": "minecraft:fishing_rod",
          "functions": [
            {
              "function": "minecraft:enchant_with_levels",
              "levels": 20
            },
            {
              "function": "minecraft:set_damage",
              "damage": {
                "min": 0,
                "max": 60
              }
            }
          ]
        },
        {
          "type": "minecraft:item",
          "weight": 3,
          "name": "minecraft:turtle_helmet",
          "functions": [
            {
              "function": "minecraft:enchant_with_levels",
              "levels": 20
            },
            {
              "function": "minecraft:set_damage",
              "damage": {
                "min": 0,
                "max": 200
              }
            }
          ]
        },
        {
          "type": "minecraft:empty",
          "weight": 10
        }
      ]
    }
  ]
}
